{
  "stage": "1013K_M1_CURRICULUM_TO_BIG_UNIT_REVIEW_MILESTONE_PACKAGE",
  "generated_at": "2026-06-21T02:18:45+00:00",
  "final_status": "PASS_1013K_M1_CURRICULUM_TO_BIG_UNIT_REVIEW_MILESTONE_PACKAGE",
  "inherits_from": "1013K_R4_STATIC_SECTION_PREVIEW_TO_REVIEW_SURFACE_FIXTURE",
  "next_stage": "1013K_R5_BIG_UNIT_REVIEW_ACTION_STATE_DRY_RUN",
  "milestone_package_created": true,
  "github_upload_ready": true,
  "github_uploaded": false,
  "all_stage_results_present": true,
  "stage_count": 5,
  "all_validators_pass": true,
  "all_failed_checks_empty": true,
  "secret_scan_hits": [],
  "runtime_connected": false,
  "provider_called": false,
  "model_called": false,
  "database_written": false,
  "memory_written": false,
  "feishu_written": false,
  "formal_apply_performed": false,
  "unit_package_written": false,
  "lesson_body_modified": false,
  "html_body_modified": false,
  "runtime_schema_applied": false,
  "official_curriculum_claim_created": false,
  "main_project_pushed": false,
  "failed_checks": [],
  "validator_pass": true
}
